{
  "listChanelConfig": [
    {
      "channelConfigName": "laodong",
      "titleXPath": "<title>(.*?)</title>",
      "descriptionXPath": "<description>(.*?)</description>",
      "linkXPath": "<link>(.*?)</link>",
      "imageXPath": "enclosure url=\"(.*?)\"",
      "pubDateXPath": "<pubDate>(.*?)</pubDate>",
      "guidXPath": "<guid isPermaLink=\"true\">(.*?)</guid>"
    },
    {
      "channelConfigName": "vnexpress",
      "titleXPath": "<title>(.*?)</title>",
      "descriptionXPath": "<description>(.*?)</description>",
      "linkXPath": "<link>(.*?)</link>",
      "imageXPath": "<img src=\"(.*?)\"",
      "pubDateXPath": "<pubDate>(.*?)</pubDate>",
      "guidXPath": "<guid>(.*?)</guid>"
    },
    {
      "channelConfigName": "tienphong",
      "titleXPath": "<title>(.*?)</title>",
      "descriptionXPath": "<description>(.*?)</description>",
      "linkXPath": "<link>(.*?)</link>",
      "imageXPath": "<image>(.*?)</image>",
      "pubDateXPath": "<pubDate>(.*?)</pubDate>",
      "guidXPath": "<guid>(.*?)</guid>"
    }
  ]
}